file/__init__.py
file/_libmagic.abi3.so
file/_libmagic_build.py
file/.libs/libz-a147dcb0.so.1.2.3
file/.libs/libmagic-c35b4bbc.so.1.0.0
file-0.2.0.dist-info/DESCRIPTION.rst
file-0.2.0.dist-info/WHEEL
file-0.2.0.dist-info/metadata.json
file-0.2.0.dist-info/METADATA
file-0.2.0.dist-info/RECORD
file-0.2.0.dist-info/top_level.txt
